codaio_exporter/__init__.py
codaio_exporter/__main__.py
codaio_exporter/api/__init__.py
codaio_exporter/api/client.py
codaio_exporter/api/column.py
codaio_exporter/api/doc.py
codaio_exporter/api/parse.py
codaio_exporter/api/row.py
codaio_exporter/api/table.py
codaio_exporter/export.py
codaio_exporter/progress.py
codaio_exporter/py.typed
codaio_exporter/reimport.py
codaio_exporter/table.py
codaio_exporter/utils/__init__.py
codaio_exporter/utils/async_app.py
codaio_exporter/utils/concurrencylimit.py
codaio_exporter/utils/gather.py
codaio_exporter/utils/generator.py
codaio_exporter/utils/ratelimit.py
codaio_exporter/utils/retry.py
codaio_exporter-0.3.4.dist-info/entry_points.txt
codaio_exporter-0.3.4.dist-info/WHEEL
codaio_exporter-0.3.4.dist-info/METADATA
codaio_exporter-0.3.4.dist-info/RECORD
