Metadata-Version: 2.1
Name: codaio-exporter
Version: 0.3.4
Summary: 
Author: Sebastian Messmer
Author-email: mail@smessmer.de
Requires-Python: >=3.10,<4.0
Classifier: Programming Language :: Python :: 3
Classifier: Programming Language :: Python :: 3.10
Requires-Dist: aiofiles (>=23.2.1,<24.0.0)
Requires-Dist: aiohttp (>=3.8.5,<4.0.0)
Requires-Dist: dataclasses-json (>=0.6.0,<0.7.0)
Requires-Dist: ensure (>=1.0.3,<2.0.0)
Requires-Dist: rich (>=13.5.2,<14.0.0)
Requires-Dist: types-PyYAML (>=6.0.12.11,<7.0.0.0)
Requires-Dist: types-aiofiles (>=23.2.0.0,<24.0.0.0)
